feedparsley/__init__.py
feedparsley/feedparsley.py
feedparsley-0.1.5.dist-info/METADATA
feedparsley-0.1.5.dist-info/WHEEL
feedparsley-0.1.5.dist-info/entry_points.txt
feedparsley-0.1.5.dist-info/top_level.txt
feedparsley-0.1.5.dist-info/RECORD
